ncti_cad/__init__.py
ncti_cad/api.py
ncti_cad/env.py
ncti_cad-0.2.1.dist-info/METADATA
ncti_cad-0.2.1.dist-info/WHEEL
ncti_cad-0.2.1.dist-info/top_level.txt
ncti_cad-0.2.1.dist-info/RECORD
