Metadata-Version: 2.4
Name: ncti-cad
Version: 0.2.1
Summary: CAD modeling API wrapper for NCTI
Requires-Python: >=3.9
Requires-Dist: numpy
Requires-Dist: numpy-stl
Requires-Dist: trimesh
